jupyter_ai_jupyternaut/__init__.py
jupyter_ai_jupyternaut/_version.py
jupyter_ai_jupyternaut/extension_app.py
jupyter_ai_jupyternaut/handlers.py
jupyter_ai_jupyternaut/config/__init__.py
jupyter_ai_jupyternaut/config/config_manager.py
jupyter_ai_jupyternaut/config/config_models.py
jupyter_ai_jupyternaut/config/config_rest_api.py
jupyter_ai_jupyternaut/jupyternaut/__init__.py
jupyter_ai_jupyternaut/jupyternaut/chat_models.py
jupyter_ai_jupyternaut/jupyternaut/jupyternaut.py
jupyter_ai_jupyternaut/jupyternaut/prompt_template.py
jupyter_ai_jupyternaut/jupyternaut/toolkits/__init__.py
jupyter_ai_jupyternaut/jupyternaut/toolkits/code_execution.py
jupyter_ai_jupyternaut/jupyternaut/toolkits/filesystem.py
jupyter_ai_jupyternaut/jupyternaut/toolkits/jupyterlab.py
jupyter_ai_jupyternaut/jupyternaut/toolkits/notebook.py
jupyter_ai_jupyternaut/jupyternaut/toolkits/utils.py
jupyter_ai_jupyternaut/models/__init__.py
jupyter_ai_jupyternaut/models/parameter_schemas.py
jupyter_ai_jupyternaut/models/parameters_rest_api.py
jupyter_ai_jupyternaut/secrets/__init__.py
jupyter_ai_jupyternaut/secrets/secrets_manager.py
jupyter_ai_jupyternaut/secrets/secrets_rest_api.py
jupyter_ai_jupyternaut/secrets/secrets_types.py
jupyter_ai_jupyternaut/secrets/secrets_utils.py
jupyter_ai_jupyternaut/secrets/tests/__init__.py
jupyter_ai_jupyternaut/secrets/tests/test_secrets_manager.py
jupyter_ai_jupyternaut/secrets/tests/test_secrets_utils.py
jupyter_ai_jupyternaut/static/jupyternaut.svg
jupyter_ai_jupyternaut/tests/__init__.py
jupyter_ai_jupyternaut/tests/test_handlers.py
jupyter_ai_jupyternaut-0.0.9.data/data/etc/jupyter/jupyter_server_config.d/jupyter_ai_jupyternaut.json
jupyter_ai_jupyternaut-0.0.9.data/data/share/jupyter/labextensions/@jupyter-ai/jupyternaut/package.json
jupyter_ai_jupyternaut-0.0.9.data/data/share/jupyter/labextensions/@jupyter-ai/jupyternaut/schemas/@jupyter-ai/jupyternaut/package.json.orig
jupyter_ai_jupyternaut-0.0.9.dist-info/METADATA
jupyter_ai_jupyternaut-0.0.9.dist-info/WHEEL
jupyter_ai_jupyternaut-0.0.9.dist-info/entry_points.txt
jupyter_ai_jupyternaut-0.0.9.dist-info/licenses/LICENSE
jupyter_ai_jupyternaut-0.0.9.dist-info/RECORD
