Metadata-Version: 2.4
Name: jupyter_ai_jupyternaut
Version: 0.0.9
Summary: Package providing the default AI persona, Jupyternaut, in Jupyter AI.
Project-URL: Homepage, https://github.com/jupyter-ai-contrib/jupyter-ai-jupyternaut
Project-URL: Bug Tracker, https://github.com/jupyter-ai-contrib/jupyter-ai-jupyternaut/issues
Project-URL: Repository, https://github.com/jupyter-ai-contrib/jupyter-ai-jupyternaut.git
Author-email: Project Jupyter <jupyter@googlegroups.com>
License: BSD 3-Clause License
License-File: LICENSE
Keywords: jupyter,jupyterlab,jupyterlab-extension
Classifier: Framework :: Jupyter
Classifier: Framework :: Jupyter :: JupyterLab
Classifier: Framework :: Jupyter :: JupyterLab :: 4
Classifier: Framework :: Jupyter :: JupyterLab :: Extensions
Classifier: Framework :: Jupyter :: JupyterLab :: Extensions :: Prebuilt
Classifier: License :: OSI Approved :: BSD License
Classifier: Programming Language :: Python
Classifier: Programming Language :: Python :: 3
Classifier: Programming Language :: Python :: 3.10
Classifier: Programming Language :: Python :: 3.11
Classifier: Programming Language :: Python :: 3.12
Classifier: Programming Language :: Python :: 3.13
Requires-Python: >=3.10
Requires-Dist: aiosqlite>=0.20
Requires-Dist: deepmerge<3,>=2.0
Requires-Dist: jinja2<4,>=3.0
Requires-Dist: jupyter-ai-litellm>=0.0.1
Requires-Dist: jupyter-ai-persona-manager>=0.0.1
Requires-Dist: jupyter-server-documents>=0.1.0a8
Requires-Dist: jupyter-server<3,>=2.15.0
Requires-Dist: jupyterlab-chat>=0.19.0a1
Requires-Dist: jupyterlab-commands-toolkit>=0.1.2
Requires-Dist: jupyterlab-notebook-awareness>=0.2.0
Requires-Dist: langchain>=1.0.0
Requires-Dist: langgraph-checkpoint-sqlite>=3.0.0
Requires-Dist: pydantic<3,>=2.10.0
Requires-Dist: python-dotenv<2,>=1
Requires-Dist: traitlets>=5.6
Provides-Extra: test
Requires-Dist: coverage; extra == 'test'
Requires-Dist: pytest; extra == 'test'
Requires-Dist: pytest-asyncio; extra == 'test'
Requires-Dist: pytest-cov; extra == 'test'
Requires-Dist: pytest-jupyter[server]>=0.6.0; extra == 'test'
